<annotation verified="yes">
                                    <folder>Annotation</folder>
                                    <filename>Cam5-From09-27-50To09-29-30-Guns_x264_frame_73</filename>
                                    <path>C:\Users\Rodrigo\Desktop\Reetiquetado con VoTT v1\Videos Rodri\JPEGImages\Cam5-From09-27-50To09-29-30-Guns_x264_frame_73.jpg</path>
                                    <source>
                                        <database>Unknown</database>
                                    </source>
                                    <size>
                                        <width>1920</width>
                                        <height>1080</height>
                                        <depth>3</depth>
                                    </size>
                                    <segmented>0</segmented>
                                    <object>
                                            <name>pistol</name>
                                            <pose>Unspecified</pose>
                                            <truncated>0</truncated>
                                            <difficult>0</difficult>
                                            <bndbox>
                                                <xmin>719.3388429752066</xmin>
                                                <ymin>243.23133414932678</ymin>
                                                <xmax>760.3305785123968</xmax>
                                                <ymax>292.14198286413705</ymax>
                                            </bndbox>
                                    </object>
                                    </annotation>