<annotation verified="yes">
                                    <folder>Annotation</folder>
                                    <filename>Cam5-From09-27-50To09-29-30-Guns_x264_frame_14</filename>
                                    <path>C:\Users\Rodrigo\Desktop\Reetiquetado con VoTT v1\Videos Rodri\JPEGImages\Cam5-From09-27-50To09-29-30-Guns_x264_frame_14.jpg</path>
                                    <source>
                                        <database>Unknown</database>
                                    </source>
                                    <size>
                                        <width>1920</width>
                                        <height>1080</height>
                                        <depth>3</depth>
                                    </size>
                                    <segmented>0</segmented>
                                    <object>
                                            <name>pistol</name>
                                            <pose>Unspecified</pose>
                                            <truncated>0</truncated>
                                            <difficult>0</difficult>
                                            <bndbox>
                                                <xmin>335.86776859504135</xmin>
                                                <ymin>478.531211750306</ymin>
                                                <xmax>390.08264462809916</xmax>
                                                <ymax>519.5104039167686</ymax>
                                            </bndbox>
                                    </object>
                                    </annotation>