<annotation verified="yes">
                                    <folder>Annotation</folder>
                                    <filename>Cam5-From09-24-18To09-26-43-Guns_x264_Segment_0_x264_frame_94</filename>
                                    <path>C:\Users\marina\Documents\DeepLearning\Images\Etiquetados editados\Cam5-From09-24-18To09-26-43-Guns_x264_Segment_0_x264_output\JPEGImages\Cam5-From09-24-18To09-26-43-Guns_x264_Segment_0_x264_frame_94.jpg</path>
                                    <source>
                                        <database>Unknown</database>
                                    </source>
                                    <size>
                                        <width>1920</width>
                                        <height>1080</height>
                                        <depth>3</depth>
                                    </size>
                                    <segmented>0</segmented>
                                    <object>
                                            <name>knife</name>
                                            <pose>Unspecified</pose>
                                            <truncated>0</truncated>
                                            <difficult>0</difficult>
                                            <bndbox>
                                                <xmin>31.735537190082646</xmin>
                                                <ymin>623.9412484700122</ymin>
                                                <xmax>71.40495867768595</xmax>
                                                <ymax>705.8996328029375</ymax>
                                            </bndbox>
                                    </object>
                                    
                                    <object>
                                            <name>pistol</name>
                                            <pose>Unspecified</pose>
                                            <truncated>0</truncated>
                                            <difficult>0</difficult>
                                            <bndbox>
                                                <xmin>486.6115702479339</xmin>
                                                <ymin>302.7172582619339</ymin>
                                                <xmax>546.1157024793389</xmax>
                                                <ymax>334.44308445532437</ymax>
                                            </bndbox>
                                    </object>
                                    
                                    <object>
                                            <name>pistol</name>
                                            <pose>Unspecified</pose>
                                            <truncated>0</truncated>
                                            <difficult>0</difficult>
                                            <bndbox>
                                                <xmin>633.3884297520661</xmin>
                                                <ymin>416.4014687882497</ymin>
                                                <xmax>659.8347107438017</xmax>
                                                <ymax>456.0587515299877</ymax>
                                            </bndbox>
                                    </object>
                                    
                                    <object>
                                            <name>pistol</name>
                                            <pose>Unspecified</pose>
                                            <truncated>0</truncated>
                                            <difficult>0</difficult>
                                            <bndbox>
                                                <xmin>822.4793388429753</xmin>
                                                <ymin>453.4149326805385</ymin>
                                                <xmax>888.595041322314</xmax>
                                                <ymax>539.3390452876376</ymax>
                                            </bndbox>
                                    </object>
                                    
                                    <object>
                                            <name>pistol</name>
                                            <pose>Unspecified</pose>
                                            <truncated>0</truncated>
                                            <difficult>0</difficult>
                                            <bndbox>
                                                <xmin>885.9504132231406</xmin>
                                                <ymin>601.468788249694</ymin>
                                                <xmax>979.8347107438017</xmax>
                                                <ymax>679.4614443084455</ymax>
                                            </bndbox>
                                    </object>
                                    
                                    <object>
                                            <name>pistol</name>
                                            <pose>Unspecified</pose>
                                            <truncated>0</truncated>
                                            <difficult>0</difficult>
                                            <bndbox>
                                                <xmin>830.4132231404959</xmin>
                                                <ymin>297.4296205630355</ymin>
                                                <xmax>876.6942148760331</xmax>
                                                <ymax>334.44308445532437</ymax>
                                            </bndbox>
                                    </object>
                                    </annotation>